{
  "dileep_mampallil": {
    "name": "Dileep Mampallil",
    "scholar_url": "https://scholar.google.com/citations?user=XXXXXX&hl=en",
    "papers": [
      {
        "id": "orcid_186395415",
        "title": "Evaporation of emulsion drops on surfaces: A short review",
        "authors": "",
        "year": "",
        "venue": "",
        "doi": "10.1016/j.cocis.2025.101938",
        "url": "/0000-0001-8851-9808/work/186395415",
	"source": "ORCID"
      },
      {
        "id": "orcid_174940349",
        "title": "Water drop on thin viscous oil layers: From stick-slip spreading to dewetting",
        "authors": "",
        "year": "",
        "venue": "",
        "doi": "10.1063/5.0246258",
        "url": "/0000-0001-8851-9808/work/174940349",
        "source": "ORCID"
      },
      {
        "id": "orcid_197255983",
        "title": "Microfluidic analysis of salt-stress-mediated antibiotic tolerance in Mycobacterium smegmatis",
        "authors": "",
        "year": "",
        "venue": "",
        "doi": "10.1039/D5LC00713E",
        "url": "/0000-0001-8851-9808/work/197255983",
        "source": "ORCID"
      },
      {
        "id": "orcid_148857934",
        "title": "Evaporative phase separation in polymer microdroplets with confinement and internal flow",
        "authors": "",
        "year": "",
        "venue": "",
        "doi": "10.1016/j.jciso.2023.100101",
        "url": "/0000-0001-8851-9808/work/148857934",
        "source": "ORCID"
      },
      {
        "id": "orcid_157064715",
        "title": "Spheroids formation in large drops suspended in superhydrophobic paper cones",
        "authors": "",
        "year": "",
        "venue": "",
        "doi": "10.1063/5.0197807",
        "url": "/0000-0001-8851-9808/work/157064715",
        "source": "ORCID"
      },
      {
        "id": "orcid_169195094",
        "title": "Dynamics of phase-separated microdroplets near the contact line of evaporating all-aqueous drops",
        "authors": "",
        "year": "",
        "venue": "",
        "doi": "10.1039/D4SM01056F",
        "url": "/0000-0001-8851-9808/work/169195094",
        "source": "ORCID"
      },
      {
        "id": "orcid_130400183",
        "title": "Distributed evaporation of water-in-oil emulsion drops on solid surfaces",
        "authors": "",
        "year": "",
        "venue": "",
        "doi": "10.1063/5.0107471",
        "url": "/0000-0001-8851-9808/work/130400183",
        "source": "ORCID"
      },
      {
        "id": "orcid_130400182",
        "title": "Microfluidic Droplet Cluster with Distributed Evaporation Rates as a Model for Bioaerosols",
        "authors": "",
        "year": "",
        "venue": "",
        "doi": "10.1021/acs.langmuir.1c03273",
        "url": "/0000-0001-8851-9808/work/130400182",
        "source": "ORCID"
      },
      {
        "id": "orcid_130400181",
        "title": "Dynamics of bacterial deposition in evaporating drops",
        "authors": "",
        "year": "",
        "venue": "",
        "doi": "10.1063/5.0024078",
        "url": "/0000-0001-8851-9808/work/130400181",
        "source": "ORCID"
      },
      {
        "id": "orcid_130400180",
        "title": "Evaporation of Inclined Drops: Formation of Asymmetric Ring Patterns",
        "authors": "",
        "year": "",
        "venue": "",
        "doi": "10.1021/acs.langmuir.0c01084",
        "url": "/0000-0001-8851-9808/work/130400180",
        "source": "ORCID"
      },
      {
        "id": "orcid_130400170",
        "title": "Drop impact on thin powder layers: pattern formation by air entrapment",
        "authors": "",
        "year": "",
        "venue": "",
        "doi": "10.1039/C9SM01887E",
        "url": "/0000-0001-8851-9808/work/130400170",
        "source": "ORCID"
      }
    ]
  },
  "jessy": {
    "name": "Jessy Jose",
    "scholar_url": "https://scholar.google.com/citations?user=lBJBBfMAAAAJ&hl=en", 
    "papers": [
      {
        "id": "orcid_198105084",
        "title": "Investigating the Influence of Radiative Feedback in the Bright-rimmed Cloud 44",
        "authors": "Rishi C, Neelam Panwar, Thomas J. Haworth, Yan Sun, Saurabh Sharma, R. K. Yadav, D.K. Ojha, H.P. Singh, Jessy Jose, Ajay Kumar Singh, Jincen Jose, Shubham Yadav",
        "year": 2025,
        "venue": "The Astrophysical Journal",
        "doi": "10.3847/1538-4357/ae0f03",
        "url": "https://doi.org/10.3847/1538-4357/ae0f03",
        "source": "CrossRef/ORCID"
      },
      {
        "id": "orcid_187208188",
        "title": "Protoplanetary disc survival time-scales: a blind survey of young clusters up to 100 Myr in the solar vicinity",
        "authors": "Gregory Mathews Ben, Jessy Jose, Jesús Hernández",
        "year": 2025,
        "venue": "Monthly Notices of the Royal Astronomical Society",
        "doi": "10.1093/mnras/staf1089",
        "url": "https://doi.org/10.1093/mnras/staf1089",
        "source": "CrossRef/ORCID"
      },
      {
        "id": "orcid_187335299",
        "title": "Exploring membership and variability in NGC 7419: an open cluster rich in supergiants and Be type stars",
        "authors": "Arghya Chakraborty, Jessy Jose, Alex C Carciofi",
        "year": 2025,
        "venue": "Monthly Notices of the Royal Astronomical Society",
        "doi": "10.1093/mnras/staf1104",
        "url": "https://doi.org/10.1093/mnras/staf1104",
        "source": "CrossRef/ORCID"
      },
      {
        "id": "orcid_184188893",
        "title": "Star formation efficiency and scaling relations in parsec-scale cluster-forming clumps",
        "authors": "Vineet Rawat, M R Samal, A Zavagno, Sami Dib, Davide Elia, J Jose, D K Ojha, K Srivastav",
        "year": 2025,
        "venue": "Monthly Notices of the Royal Astronomical Society",
        "doi": "10.1093/mnras/staf807",
        "url": "https://doi.org/10.1093/mnras/staf807",
        "source": "CrossRef/ORCID"
      },
      {
        "id": "orcid_186782654",
        "title": "Subaru Hyper-Supreme Cam observations of IC 1396",
        "authors": "Swagat R. Das, Saumya Gupta, Jessy Jose, Manash Samal, J. Gregory Herczeg, Zhen Guo, Surhud More, Prem Prakash",
        "year": 2025,
        "venue": "Astronomy &amp; Astrophysics",
        "doi": "10.1051/0004-6361/202450428",
        "url": "https://doi.org/10.1051/0004-6361/202450428",
        "source": "CrossRef/ORCID"
      },
      {
        "id": "orcid_182264350",
        "title": "Variation of Dense Gas Mass–Luminosity Conversion Factor with Metallicity in the Milky Way",
        "authors": "Sudeshna Patra, Neal J. Evans, Kee-Tae Kim, Mark Heyer, Andrea Giannetti, Davide Elia, Jessy Jose, Jens Kauffmann, Manash R. Samal, Agata Karska, Swagat R. Das, Gyuho Lee, Geumsook Park",
        "year": 2025,
        "venue": "The Astrophysical Journal",
        "doi": "10.3847/1538-4357/adbf8d",
        "url": "https://doi.org/10.3847/1538-4357/adbf8d",
        "source": "CrossRef/ORCID"
      },
      {
        "id": "orcid_178076515",
        "title": "A Novel Survey for Young Substellar Objects with the W-band Filter. VII. Water-bearing Objects in the Core of the ρ Ophiuchi Cloud Complex",
        "authors": "Tanvi Sharma, Wen Ping Chen, Beth Biller, Loïc Albert, Belinda Damian, Jessy Jose, Bhavana Lalchand, Michael C. Liu, Yumiko Oasa",
        "year": 2025,
        "venue": "The Astrophysical Journal",
        "doi": "10.3847/1538-4357/ada3c3",
        "url": "https://doi.org/10.3847/1538-4357/ada3c3",
        "source": "CrossRef/ORCID"
      },
      {
        "id": "orcid_170573606",
        "title": "Twins in diversity: understanding circumstellar disc evolution in the twin clusters of W5 complex",
        "authors": "Belinda Damian, Jessy Jose, Swagat R Das, Saumya Gupta, Vignesh Vaikundaraman, D K Ojha, Sreeja S Kartha, Neelam Panwar, Chakali Eswaraiah",
        "year": 2024,
        "venue": "Monthly Notices of the Royal Astronomical Society",
        "doi": "10.1093/mnras/stae2452",
        "url": "https://doi.org/10.1093/mnras/stae2452",
        "source": "CrossRef/ORCID"
      },
      {
        "id": "orcid_166500758",
        "title": "Peering into the Heart of the Giant Molecular Cloud G148.24+00.41: A Deep Near-infrared View of the Newly Hatched Cluster FSR 655",
        "authors": "Vineet Rawat, M. R. Samal, D. K. Ojha, Brajesh Kumar, Saurabh Sharma, J. Jose, Ram Sagar, R. K. Yadav",
        "year": 2024,
        "venue": "The Astronomical Journal",
        "doi": "10.3847/1538-3881/ad630d",
        "url": "https://doi.org/10.3847/1538-3881/ad630d",
        "source": "CrossRef/ORCID"
      },
      {
        "id": "orcid_163867296",
        "title": "Does Metallicity Affect the Protoplanetary Disk Fraction? Answers from the Outer Milky Way",
        "authors": "Sudeshna Patra, Jessy Jose, Neal J. Evans",
        "year": 2024,
        "venue": "The Astrophysical Journal",
        "doi": "10.3847/1538-4357/ad4996",
        "url": "https://doi.org/10.3847/1538-4357/ad4996",
        "source": "CrossRef/ORCID"
      },
      {
        "id": "orcid_152236719",
        "title": "Search for brown dwarfs in IC 1396 with <i>Subaru</i> HSC: interpreting the impact of environmental factors on substellar population",
        "authors": "Saumya Gupta, Jessy Jose, Swagat R Das, Zhen Guo, Belinda Damian, Prem Prakash, Manash R Samal",
        "year": 2024,
        "venue": "Monthly Notices of the Royal Astronomical Society",
        "doi": "10.1093/mnras/stae369",
        "url": "https://doi.org/10.1093/mnras/stae369",
        "source": "CrossRef/ORCID"
      },
      {
        "id": "orcid_150111713",
        "title": "The Giant Molecular Cloud G148.24+00.41: gas properties, kinematics, and cluster formation at the nexus of filamentary flows",
        "authors": "Vineet Rawat, M R Samal, D L Walker, D K Ojha, A Tej, A Zavagno, C P Zhang, Davide Elia, S Dutta, J Jose, C Eswaraiah, E Sharma",
        "year": 2024,
        "venue": "Monthly Notices of the Royal Astronomical Society",
        "doi": "10.1093/mnras/stae060",
        "url": "https://doi.org/10.1093/mnras/stae060",
        "source": "CrossRef/ORCID"
      },
      {
        "id": "orcid_150087148",
        "title": "Understanding the relative importance of magnetic field, gravity, and turbulence in star formation at the hub of the giant molecular cloud G148.24+00.41",
        "authors": "Vineet Rawat, M R Samal, Chakali Eswaraiah, Jia-Wei Wang, Davide Elia, Sandhyarani Panigrahy, A Zavagno, R K Yadav, D L Walker, J Jose, D K Ojha, C P Zhang, S Dutta",
        "year": 2024,
        "venue": "Monthly Notices of the Royal Astronomical Society",
        "doi": "10.1093/mnras/stae053",
        "url": "https://doi.org/10.1093/mnras/stae053",
        "source": "CrossRef/ORCID"
      },
      {
        "id": "orcid_149005071",
        "title": "An outburst and FU Ori-type disc of a former low-luminosity protostar",
        "authors": "Mizna Ashraf, Jessy Jose, Ho-Gyu Lee, Carlos Contreras Peña, Gregory J Herczeg, Hanpu Liu, Doug Johnstone, Jeong-Eun Lee",
        "year": 2023,
        "venue": "Monthly Notices of the Royal Astronomical Society",
        "doi": "10.1093/mnras/stad3900",
        "url": "https://doi.org/10.1093/mnras/stad3900",
        "source": "CrossRef/ORCID"
      },
      {
        "id": "orcid_143153383",
        "title": "Correction to: Revealing the dust grain polarization properties as a function of extinction and distance towards NGC 1893",
        "authors": "N Bijas, Chakali Eswaraiah, Jia-Wei Wang, Jessy Jose, Wen-Ping Chen, Di Li, Shih-Ping Lai, D K Ojha",
        "year": 2023,
        "venue": "Monthly Notices of the Royal Astronomical Society",
        "doi": "10.1093/mnras/stad2880",
        "url": "https://doi.org/10.1093/mnras/stad2880",
        "source": "CrossRef/ORCID"
      },
      {
        "id": "orcid_140545339",
        "title": "Protoplanetary disks around young stellar and substellar objects in the $${\\sigma }$$ Orionis cluster",
        "authors": "Belinda Damian, Jessy Jose, Beth Biller, K. T. Paul",
        "year": 2023,
        "venue": "Journal of Astrophysics and Astronomy",
        "doi": "10.1007/s12036-023-09968-2",
        "url": "https://doi.org/10.1007/s12036-023-09968-2",
        "source": "CrossRef/ORCID"
      },
      {
        "id": "orcid_138472513",
        "title": "A Novel Survey for Young Substellar Objects with the W-band Filter. VI. Spectroscopic Census of Substellar Members and the IMF of the σ Orionis Cluster",
        "authors": "Belinda Damian, Jessy Jose, Beth Biller, Gregory J. Herczeg, Loïc Albert, Katelyn Allers, Zhoujian Zhang, Michael C. Liu, Sophie Dubber, KT Paul, Wen-Ping Chen, Bhavana Lalchand, Tanvi Sharma, Yumiko Oasa",
        "year": 2023,
        "venue": "The Astrophysical Journal",
        "doi": "10.3847/1538-4357/acd115",
        "url": "https://doi.org/10.3847/1538-4357/acd115",
        "source": "CrossRef/ORCID"
      },
      {
        "id": "orcid_137053491",
        "title": "Role of magnetic fields in the fragmentation of the Taurus B213 filament into Sun-type star-forming cores",
        "authors": "R. Anirudh, Chakali Eswaraiah, Sihan Jiao, Jessy Jose",
        "year": 2023,
        "venue": "Journal of Astrophysics and Astronomy",
        "doi": "10.1007/s12036-023-09948-6",
        "url": "https://doi.org/10.1007/s12036-023-09948-6",
        "source": "CrossRef/ORCID"
      },
      {
        "id": "orcid_133875394",
        "title": "Membership Analysis and 3D Kinematics of the Star-forming Complex around Trumpler 37 Using Gaia-DR3",
        "authors": "Swagat R. Das, Saumya Gupta, Prem Prakash, Manash Samal, Jessy Jose",
        "year": 2023,
        "venue": "The Astrophysical Journal",
        "doi": "10.3847/1538-4357/acbf54",
        "url": "https://doi.org/10.3847/1538-4357/acbf54",
        "source": "CrossRef/ORCID"
      },
      {
        "id": "orcid_129879072",
        "title": "Probing the global dust properties and cluster formation potential of the giant molecular cloud G148.24+00.41",
        "authors": "Vineet Rawat, M R Samal, D L Walker, A Zavagno, A Tej, G Marton, D K Ojha, Davide Elia, W P Chen, J Jose, C Eswaraiah",
        "year": 2023,
        "venue": "Monthly Notices of the Royal Astronomical Society",
        "doi": "10.1093/mnras/stad639",
        "url": "https://doi.org/10.1093/mnras/stad639",
        "source": "CrossRef/ORCID"
      },
      {
        "id": "orcid_128366915",
        "title": "A novel survey for young substellar objects with the <i>W</i>-band filter IV: detection and characterization of low-mass brown dwarfs in Serpens Core",
        "authors": "Sophie Dubber, Beth Biller, Loïc Albert, Michael Liu, Jessy Jose, Zhoujian Zhang, Wen-Ping Chen, Bhavana Lalchand, Belinda Damian, Tanvi Sharma, Katelyn Allers",
        "year": 2023,
        "venue": "Monthly Notices of the Royal Astronomical Society",
        "doi": "10.1093/mnras/stad283",
        "url": "https://doi.org/10.1093/mnras/stad283",
        "source": "CrossRef/ORCID"
      },
      {
        "id": "orcid_118535280",
        "title": "A Novel Survey for Young Substellar Objects with the W-band Filter. V. IC 348 and Barnard 5 in the Perseus Cloud",
        "authors": "Bhavana Lalchand, Wen-Ping Chen, Beth A. Biller, Loïc Albert, Katelyn Allers, Sophie Dubber, Zhoujian Zhang, Michael C. Liu, Jessy Jose, Belinda Damian, Tanvi Sharma, Mickaël Bonnefoy, Yumiko Oasa",
        "year": 2022,
        "venue": "The Astronomical Journal",
        "doi": "10.3847/1538-3881/ac8547",
        "url": "https://doi.org/10.3847/1538-3881/ac8547",
        "source": "CrossRef/ORCID"
      },
      {
        "id": "orcid_118585614",
        "title": "Tracers of Dense Gas in the Outer Galaxy",
        "authors": "Sudeshna Patra, Neal J. Evans II, Kee-Tae Kim, Mark Heyer, Jens Kauffmann, Jessy Jose, Manash R. Samal, Swagat R. Das",
        "year": 2022,
        "venue": "The Astronomical Journal",
        "doi": "10.3847/1538-3881/ac83af",
        "url": "https://doi.org/10.3847/1538-3881/ac83af",
        "source": "CrossRef/ORCID"
      },
      {
        "id": "orcid_116879810",
        "title": "Revealing the dust grain polarization properties as a function of extinction and distance towards NGC 1893",
        "authors": "N Bijas, Chakali Eswaraiah, Jia-Wei Wang, Jessy Jose, Wen-Ping Chen, Di Li, Shih-Ping Lai, D K Ojha",
        "year": 2022,
        "venue": "Monthly Notices of the Royal Astronomical Society",
        "doi": "10.1093/mnras/stac1927",
        "url": "https://doi.org/10.1093/mnras/stac1927",
        "source": "CrossRef/ORCID"
      }
    ]
  },
  "nihar": {
    "name": "Nihar Sahoo",
	"scholar_url":"https://scholar.google.com/citations?user=jZADx9AAAAAJ&hl=en",
    "papers": [
      {
        "id": "orcid_121684054",
        "title": "An overview of recent STAR jet measurements",
        "authors": "Sahoo, N.R.",
        "year": "",
        "venue": "",
        "doi": "",
        "url": "http://www.scopus.com/inward/record.url?eid=2-s2.0-85124513877&partnerID=MN8TOARS",
        "source": "ORCID"
      }
    ]
  }
}